{
    "type": "minecraft:crafting_shaped",
    "pattern": [
        " F",
        "IL",
        " B"
    ],
    "key": {
        "F": {
            "item": "minecraft:flint_and_steel"
        },
        "L": {
            "type": "forge:ore_dict",
            "ore": "logWood"
        },
        "B": {
            "item": "minecraft:stone_button"
        },
        "I": {
            "type": "forge:ore_dict",
            "ore": "ingotSilver"
        }
    },
    "result": {
        "item": "huntersdream:flintlock_pistol",
        "count": 1
    }
}